mcserver/__init__.py
mcserver/parser.py
mcserver/si.py
MCServerInterface-0.0.2.dist-info/METADATA
MCServerInterface-0.0.2.dist-info/WHEEL
MCServerInterface-0.0.2.dist-info/top_level.txt
MCServerInterface-0.0.2.dist-info/RECORD
