Metadata-Version: 2.1
Name: MCServerInterface
Version: 0.0.2
Summary: Integratable API for Local Minecraft Servers
Home-page: https://github.com/TeamNightSky/MCServerWrapper
Author: Pixymon
Author-email: nlarsen23.student@gmail.com
License: GNU License
Platform: UNKNOWN
Requires-Dist: requests
